MANIFEST.in
README.rst
setup.py
Poundpay.egg-info/PKG-INFO
Poundpay.egg-info/SOURCES.txt
Poundpay.egg-info/dependency_links.txt
Poundpay.egg-info/requires.txt
Poundpay.egg-info/top_level.txt
docs/Makefile
docs/api.rst
docs/conf.py
docs/index.rst
poundpay/__init__.py
poundpay/charge_permissions.py
poundpay/client.py
poundpay/developers.py
poundpay/payments.py
poundpay/resource.py
poundpay/users.py
poundpay/utils.py
tests/__init__.py
tests/test_charge_permissions.py
tests/test_client.py
tests/test_developers.py
tests/test_payments.py
tests/test_poundpay.py
tests/test_resource.py
tests/test_users.py
tests/test_utils.py