Metadata-Version: 1.0
Name: Poundpay
Version: 0.5.1
Summary: Payments platform for marketplaces
Home-page: https://dev.poundpay.com/
Author: Matin Tamizi, Mahmoud Abdelkader
Author-email: devsupport@poundpay.com
License: BSD
Platform: UNKNOWN
Classifier: Intended Audience :: Developers
Classifier: License :: OSI Approved :: BSD License
Classifier: Programming Language :: Python
Classifier: Topic :: Software Development :: Libraries :: Python Modules
